cppstyle
