Metadata-Version: 1.0
Name: cppstyle
Version: 0.2.3
Summary: Checks C/C++ code along an clang AST.
Home-page: http://github.com/gfelbing/cppstyle
Author: Georg Felbinger
Author-email: gfelbing@github.com
License: GPLv3
Platform: UNKNOWN
